LICENSE
README.md
netbox_metrics_ext/__init__.py
netbox_metrics_ext/api/__init__.py
netbox_metrics_ext/api/urls.py
netbox_metrics_ext/api/views.py
netbox_metrics_ext/management/__init__.py
netbox_metrics_ext/management/commands/__init__.py
netbox_metrics_ext/management/commands/rqworker_metrics.py
netbox_metrics_ext/metrics.py
netbox_metrics_ext/tests/__init__.py
netbox_metrics_ext/tests/test_endpoints.py
netbox_metrics_ext/tests/test_registry.py
ntc_netbox_plugin_metrics_ext-1.0.0.dist-info/LICENSE
ntc_netbox_plugin_metrics_ext-1.0.0.dist-info/WHEEL
ntc_netbox_plugin_metrics_ext-1.0.0.dist-info/METADATA
ntc_netbox_plugin_metrics_ext-1.0.0.dist-info/RECORD
