Metadata-Version: 2.1
Name: ntc-netbox-plugin-metrics-ext
Version: 1.0.0
Summary: Plugin to improve the instrumentation of NetBox and expose additional metrics (Application Metrics, RQ Worker).
Home-page: https://github.com/networktocode/ntc-netbox-plugin-metrics-ext
License: Apache-2.0
Keywords: netbox,netbox-plugin
Author: Network to Code, LLC
Author-email: info@networktocode.com
Requires-Python: >=3.6,<4.0
Classifier: License :: OSI Approved :: Apache Software License
Classifier: Programming Language :: Python :: 3
Classifier: Programming Language :: Python :: 3.6
Classifier: Programming Language :: Python :: 3.7
Classifier: Programming Language :: Python :: 3.8
Requires-Dist: invoke (>=1.4.1,<2.0.0)
Project-URL: Repository, https://github.com/networktocode/ntc-netbox-plugin-metrics-ext
